MANIFEST.in
Makefile
README
bfwinstance
setup.cfg
setup.py
test/__init__.py
test/__init__.pyc
test/test_commands.py
test/test_plugin_integration.py
test/test_web.py
test/__pycache__/test_commands.cpython-27-PYTEST.pyc
test/__pycache__/test_plugin_integration.cpython-27-PYTEST.pyc
test/__pycache__/test_web.cpython-27-PYTEST.pyc
tiddlywebplugins/__init__.py
tiddlywebplugins.bfw.egg-info/PKG-INFO
tiddlywebplugins.bfw.egg-info/SOURCES.txt
tiddlywebplugins.bfw.egg-info/dependency_links.txt
tiddlywebplugins.bfw.egg-info/namespace_packages.txt
tiddlywebplugins.bfw.egg-info/not-zip-safe
tiddlywebplugins.bfw.egg-info/requires.txt
tiddlywebplugins.bfw.egg-info/top_level.txt
tiddlywebplugins/bfw/__init__.py
tiddlywebplugins/bfw/commands.py
tiddlywebplugins/bfw/config.py
tiddlywebplugins/bfw/instance.py
tiddlywebplugins/bfw/middleware.py
tiddlywebplugins/bfw/plugin.py
tiddlywebplugins/bfw/routing.py
tiddlywebplugins/bfw/util.py
tiddlywebplugins/bfw/web.py
tiddlywebplugins/bfw/assets/checklists.js
tiddlywebplugins/bfw/assets/contents.css
tiddlywebplugins/bfw/assets/editor.css
tiddlywebplugins/bfw/assets/editor.js
tiddlywebplugins/bfw/assets/favicon.ico
tiddlywebplugins/bfw/assets/jquery.js
tiddlywebplugins/bfw/assets/layout.css
tiddlywebplugins/bfw/assets/page.js
tiddlywebplugins/bfw/assets/pure.css
tiddlywebplugins/bfw/assets/selectize.css
tiddlywebplugins/bfw/assets/selectize.js
tiddlywebplugins/bfw/assets/widearea.css
tiddlywebplugins/bfw/assets/widearea.js
tiddlywebplugins/bfw/resources/store/bags/meta/description
tiddlywebplugins/bfw/resources/store/bags/meta/policy
tiddlywebplugins/bfw/resources/store/bags/meta/tiddlers/index/1
tiddlywebplugins/templates/dashboard.html
tiddlywebplugins/templates/editor.html
tiddlywebplugins/templates/error.html
tiddlywebplugins/templates/frontpage.html
tiddlywebplugins/templates/layout.html
tiddlywebplugins/templates/wiki_page.html