Metadata-Version: 1.1
Name: tiddlywebplugins.bfw
Version: 0.0.1
Summary: Barely Functioning Wiki
Home-page: https://github.com/FND/tiddlywebplugins.bfw
Author: FND
Author-email: UNKNOWN
License: MIT
Platform: Posix; MacOS X; Windows
Classifier: Environment :: Web Environment
Classifier: Topic :: Internet :: WWW/HTTP :: WSGI :: Application
Classifier: License :: OSI Approved :: BSD License
Classifier: Operating System :: OS Independent
Classifier: Programming Language :: Python :: 2
